rcds/__init__.py
rcds/backend/__init__.py
rcds/backend/backend.py
rcds/backends/__init__.py
rcds/backends/k8s/__init__.py
rcds/backends/k8s/backend.py
rcds/backends/k8s/jinja.py
rcds/backends/k8s/manifests.py
rcds/backends/k8s/options.schema.yaml
rcds/backends/k8s/templates/_helpers.jinja
rcds/backends/k8s/templates/deployment.yaml
rcds/backends/k8s/templates/ingress.yaml
rcds/backends/k8s/templates/namespace.yaml
rcds/backends/k8s/templates/network-policy.yaml
rcds/backends/k8s/templates/secret.yaml
rcds/backends/k8s/templates/service.yaml
rcds/backends/rctf/__init__.py
rcds/backends/rctf/backend.py
rcds/backends/rctf/options.schema.yaml
rcds/backends/rctf/rctf.py
rcds/challenge/__init__.py
rcds/challenge/challenge.py
rcds/challenge/challenge.schema.yaml
rcds/challenge/config.py
rcds/challenge/docker.py
rcds/cli/__init__.py
rcds/cli/__main__.py
rcds/cli/deploy.py
rcds/errors.py
rcds/project/__init__.py
rcds/project/assets.py
rcds/project/config.py
rcds/project/project.py
rcds/project/rcds.schema.yaml
rcds/py.typed
rcds/util/__init__.py
rcds/util/deep_merge.py
rcds/util/find.py
rcds/util/jsonschema.py
rcds/util/load.py
rcds_umdcsec-0.2.6.dist-info/LICENSE
rcds_umdcsec-0.2.6.dist-info/METADATA
rcds_umdcsec-0.2.6.dist-info/WHEEL
rcds_umdcsec-0.2.6.dist-info/entry_points.txt
rcds_umdcsec-0.2.6.dist-info/RECORD
