Metadata-Version: 2.3
Name: rcds-umdcsec
Version: 0.2.6
Summary: An automated CTF challenge deployment tool
License: BSD-3-Clause
Author: redpwn
Author-email: contact@redpwn.net
Requires-Python: >=3.8,<4.0
Classifier: License :: OSI Approved :: BSD License
Classifier: Programming Language :: Python :: 3
Classifier: Programming Language :: Python :: 3.8
Classifier: Programming Language :: Python :: 3.9
Classifier: Programming Language :: Python :: 3.10
Classifier: Programming Language :: Python :: 3.11
Classifier: Programming Language :: Python :: 3.12
Classifier: Programming Language :: Python :: 3.13
Provides-Extra: docs
Requires-Dist: Jinja2 (>=2.11.2,<4.0.0)
Requires-Dist: click (>=7.1.2,<8.0.0)
Requires-Dist: dataclasses (>=0.7,<0.9) ; python_version == "3.6"
Requires-Dist: docker (>=7.0.0,<8.0.0)
Requires-Dist: jsonschema (>=3.2.0,<4.0.0)
Requires-Dist: kubernetes (>=29.0.0,<30.0.0)
Requires-Dist: pathspec (>=0.12.1,<0.13.0)
Requires-Dist: pyyaml (>=6.0.1,<7.0.0)
Requires-Dist: requests (>=2.31.0,<3.0.0)
Requires-Dist: requests-toolbelt (>=1.0.0,<2.0.0)
Project-URL: Homepage, https://rcds.redpwn.net
Project-URL: Repository, https://github.com/redpwn/rCDS
